Metadata-Version: 2.1
Name: slybot
Version: 0.13.3
Summary: Slybot crawler
Home-page: http://github.com/scrapinghub/portia
Author: Scrapy project
Author-email: info@scrapy.org
License: BSD
Platform: Any
Classifier: Development Status :: 4 - Beta
Classifier: License :: OSI Approved :: BSD License
Classifier: Operating System :: OS Independent
Classifier: Programming Language :: Python
Classifier: Programming Language :: Python :: 2
Classifier: Programming Language :: Python :: 2.7
Classifier: Programming Language :: Python :: 3
Classifier: Programming Language :: Python :: 3.4
Requires-Dist: Scrapy
Requires-Dist: scrapely
Requires-Dist: loginform
Requires-Dist: lxml
Requires-Dist: jsonschema
Requires-Dist: dateparser
Requires-Dist: scrapy-splash
Requires-Dist: page-finder
Requires-Dist: six
Requires-Dist: chardet
Provides-Extra: clustering
Requires-Dist: page-clustering ; extra == 'clustering'
Provides-Extra: tests
Requires-Dist: nose ; extra == 'tests'
Requires-Dist: nose-timer ; extra == 'tests'
Requires-Dist: doctest-ignore-unicode ; extra == 'tests'
Requires-Dist: tox ; extra == 'tests'
